[{"name":"liberty_bsc","avatar":"https://pbs.twimg.com/profile_images/1932710837376139265/I6CX0Hfz.jpg","username":"Torch of Liberty","content":"buy the dip \uD83E\uDD2D\n\n#Liberty #RWA #BNB https://t.co/1iHrnPjPU7","url":"https://twitter.com/liberty_bsc/status/1967925244242595840","createTicket":1758024915},{"name":"egll_american","avatar":"https://pbs.twimg.com/profile_images/1926994213121458176/lWielTbn.png","username":"EaglesLanding\uD83E\uDD85","content":"Digging MERICA gold\uD83E\uDE99\n&amp; Living your life \uD83C\uDFD6️\nOnly in USD1 and HODL!\n☝️\uD83E\uDD85\n\n#EGL1 #USD1 ...","url":"https://twitter.com/EGLL_american/status/1967845367887921560","createTicket":1758005871},{"name":"worldlibertyfi","avatar":"https://pbs.twimg.com/profile_images/1819121309126729728/30Q2SFVH.jpg","username":"WLFI","content":"WLFI, in collaboration with @bonk_fun and @RaydiumProtocol, is making available up to mult...","url":"https://twitter.com/worldlibertyfi/status/1967604556541407676","createTicket":1757948457},{"name":"egll_american","avatar":"https://pbs.twimg.com/profile_images/1926994213121458176/lWielTbn.png","username":"EaglesLanding\uD83E\uDD85","content":"Game's on! \nNew challenge and pursue will be set in new week.\n\uD83E\uDD85\uD83C\uDFAE☝️\nyou ready? \n\n#EGL1 #W...","url":"https://twitter.com/EGLL_american/status/1967425090024620135","createTicket":1757905669},{"name":"liberty_bsc","avatar":"https://pbs.twimg.com/profile_images/1932710837376139265/I6CX0Hfz.jpg","username":"Torch of Liberty","content":"\uD83C\uDF31 Weekend vibes. Touch grass, breathe free.\n\n#Liberty #USD1 #WLFI https://t.co/6Lvysg6cfw","url":"https://twitter.com/liberty_bsc/status/1967229018086031521","createTicket":1757858921},{"name":"liberty_bsc","avatar":"https://pbs.twimg.com/profile_images/1932710837376139265/I6CX0Hfz.jpg","username":"Torch of Liberty","content":"Forget Wall Street — Liberty is how Main Street goes onchain.\n\n#Liberty #RWA #WLFI #USD1 h...","url":"https://twitter.com/liberty_bsc/status/1966891830840299806","createTicket":1757778530},{"name":"BUILDonBsc_AI","avatar":"https://pbs.twimg.com/profile_images/1913910456781340672/T7asvmCb.jpg","username":"BUILDON GALAXY","content":"They chase pumps\nWe stack utility\nThat’s the power of BUILDING\uD83E\uDD81\n\n#BuildWithUSD1 $B #USD1 ...","url":"https://twitter.com/BUILDonBsc_AI/status/1966881642263544182","createTicket":1757776101},{"name":"egll_american","avatar":"https://pbs.twimg.com/profile_images/1926994213121458176/lWielTbn.png","username":"EaglesLanding\uD83E\uDD85","content":"It's weekend ahead!\nFriyay vibes!\n\uD83E\uDD85☝\n\n#EGL1 #USD1 #WLFI #FridayVibes https://t.co/dJZ54ht...","url":"https://twitter.com/EGLL_american/status/1966358904960606400","createTicket":1757651470},{"name":"worldlibertyfi","avatar":"https://pbs.twimg.com/profile_images/1819121309126729728/30Q2SFVH.jpg","username":"WLFI","content":"Proposal is LIVE: route 100% of WLFI Treasury liquidity fees to market-buy $WLFI and perma...","url":"https://twitter.com/worldlibertyfi/status/1966248189998084122","createTicket":1757625074},{"name":"BUILDonBsc_AI","avatar":"https://pbs.twimg.com/profile_images/1913910456781340672/T7asvmCb.jpg","username":"BUILDON GALAXY","content":"Stability isn’t spoken, it’s built.\nEvery block, every launch, every use case\uD83E\uDD81\n\n#BuildWit...","url":"https://twitter.com/BUILDonBsc_AI/status/1966155305148125428","createTicket":1757602928},{"name":"worldlibertyfi","avatar":"https://pbs.twimg.com/profile_images/1819121309126729728/30Q2SFVH.jpg","username":"WLFI","content":"We are deeply saddened by the loss of our dear friend @charliekirk11. Charlie’s faith, cou...","url":"https://twitter.com/worldlibertyfi/status/1966137572574589109","createTicket":1757598701},{"name":"liberty_bsc","avatar":"https://pbs.twimg.com/profile_images/1932710837376139265/I6CX0Hfz.jpg","username":"Torch of Liberty","content":"RWA ≠ buzzword. \n\nRWA = Apple, Tesla, Google — on-chain, backed, and tradable with #USD1. ...","url":"https://twitter.com/liberty_bsc/status/1966137396350824848","createTicket":1757598659},{"name":"egll_american","avatar":"https://pbs.twimg.com/profile_images/1926994213121458176/lWielTbn.png","username":"EaglesLanding\uD83E\uDD85","content":"Father, fighter, beloved patriot!\nrest in peace @charliekirk11 \nAmerican Eagle spirit has ...","url":"https://twitter.com/EGLL_american/status/1966001556446392368","createTicket":1757566272},{"name":"worldlibertyfi","avatar":"https://pbs.twimg.com/profile_images/1819121309126729728/30Q2SFVH.jpg","username":"WLFI","content":"Introducing Project Wings: The Eagle Takes Off! \uD83E\uDD85\n\n- A new chapter for USD1 on Solana, al...","url":"https://twitter.com/worldlibertyfi/status/1965842750462730319","createTicket":1757528409},{"name":"worldlibertyfi","avatar":"https://pbs.twimg.com/profile_images/1819121309126729728/30Q2SFVH.jpg","username":"WLFI","content":"Adoption continues as our community keeps growing\uD83D\uDD25 USD1 will be used as the exclusive sta...","url":"https://twitter.com/worldlibertyfi/status/1965769042381480264","createTicket":1757510836},{"name":"egll_american","avatar":"https://pbs.twimg.com/profile_images/1926994213121458176/lWielTbn.png","username":"EaglesLanding\uD83E\uDD85","content":"Who's up there scrolling and vibin?\n\uD83C\uDDFA\uD83C\uDDF8\uD83E\uDD85\n\n#AppleEvent #EGL1 #USD1 #WLFI #iPhone17 #Ameri...","url":"https://twitter.com/EGLL_american/status/1965623051313447221","createTicket":1757476029},{"name":"egll_american","avatar":"https://pbs.twimg.com/profile_images/1926994213121458176/lWielTbn.png","username":"EaglesLanding\uD83E\uDD85","content":"relentless, and yes we are taking the initiative. \n\uD83E\uDD85☝\n#EGL1 #USD1 #WLFI #BNB #HODL https:...","url":"https://twitter.com/EGLL_american/status/1965273580931088689","createTicket":1757392709},{"name":"BUILDonBsc_AI","avatar":"https://pbs.twimg.com/profile_images/1913910456781340672/T7asvmCb.jpg","username":"BUILDON GALAXY","content":"Day by day, brick by brick — we keep BUILDing\uD83E\uDD81\n\n#BuildWithUSD1 $B #USD1 #WLFI https://t.c...","url":"https://twitter.com/BUILDonBsc_AI/status/1965051813574721600","createTicket":1757339835},{"name":"liberty_bsc","avatar":"https://pbs.twimg.com/profile_images/1932710837376139265/I6CX0Hfz.jpg","username":"Torch of Liberty","content":"Bringing Wall Street on-chain.\n\nLiberty Finance is building the bridge between traditional...","url":"https://twitter.com/liberty_bsc/status/1965010363323449851","createTicket":1757329953},{"name":"egll_american","avatar":"https://pbs.twimg.com/profile_images/1926994213121458176/lWielTbn.png","username":"EaglesLanding\uD83E\uDD85","content":"brand new great week ahead, keep building, my fellow eagles!\n\uD83E\uDD85☝️\n\n#EGL1 #USD1 #WLFI #BNB ...","url":"https://twitter.com/EGLL_american/status/1964878311097831929","createTicket":1757298469}]